msinfo/__init__.py
msinfo-0.0.1.dist-info/LICENSE
msinfo-0.0.1.dist-info/METADATA
msinfo-0.0.1.dist-info/WHEEL
msinfo-0.0.1.dist-info/top_level.txt
msinfo-0.0.1.dist-info/RECORD
